microsoft_store_scraper/__init__.py
microsoft_store_scraper/exceptions.py
microsoft_store_scraper/constants/__init__.py
microsoft_store_scraper/constants/regex.py
microsoft_store_scraper/constants/request.py
microsoft_store_scraper/features/__init__.py
microsoft_store_scraper/features/app.py
microsoft_store_scraper/features/search.py
microsoft_store_scraper/utils/__init__.py
microsoft_store_scraper/utils/request.py
microsoft_store_scraper-0.0.2.dist-info/METADATA
microsoft_store_scraper-0.0.2.dist-info/WHEEL
microsoft_store_scraper-0.0.2.dist-info/licenses/LICENSE
microsoft_store_scraper-0.0.2.dist-info/RECORD
